airsupply/__init__.py
airsupply/__main__.py
airsupply/apk.py
airsupply/cli.py
airsupply/html.jinja2
airsupply/ipa.py
airsupply/ipa_manifest.jinja2
airsupply/local.py
airsupply/push.py
airsupply/s3.py
airsupply/templates.py
airsupply-0.4.1.dist-info/METADATA
airsupply-0.4.1.dist-info/WHEEL
airsupply-0.4.1.dist-info/entry_points.txt
airsupply-0.4.1.dist-info/RECORD
