Metadata-Version: 2.1
Name: airsupply
Version: 0.4.1
Summary: Manage OTA distribution for IPA and APK files.
License: MIT
Author: Michael Merickel
Requires-Python: >=3.7
Classifier: License :: OSI Approved :: MIT License
Classifier: Programming Language :: Python :: 3
Classifier: Programming Language :: Python :: 3.7
Classifier: Programming Language :: Python :: 3.8
Classifier: Programming Language :: Python :: 3.9
Classifier: Programming Language :: Python :: 3.10
Classifier: Programming Language :: Python :: 3.11
Requires-Dist: attrs (>=20.2.0)
Requires-Dist: boto3 (>=1.14.0)
Requires-Dist: click (>=7.0)
Requires-Dist: jinja2 (>=2.10.3)
Requires-Dist: pyaxmlparser (>=0.3.24)
Requires-Dist: pyipng (>=1.0.3,<2.0.0)
